Metadata-Version: 1.1
Name: pycallgraph
Version: 1.0.0
Summary: Python Call Graph is a library and command line tool that visualises the flow of your Python application.  See http://pycallgraph.slowchop.com/ for more information.
Home-page: http://pycallgraph.slowchop.com/
Author: Gerald Kaszuba
Author-email: pycallgraph@gakman.com
License: 		    GNU GENERAL PUBLIC LICENSE
